tm1cli/__init__.py
tm1cli/commands/__init__.py
tm1cli/commands/cube.py
tm1cli/commands/dimension.py
tm1cli/commands/process.py
tm1cli/commands/subset.py
tm1cli/commands/view.py
tm1cli/main.py
tm1cli/utils/__init__.py
tm1cli/utils/cli_param.py
tm1cli/utils/tm1yaml.py
tm1cli/utils/various.py
tm1cli/utils/watch.py
tm1cli-0.1.7.dist-info/LICENSE
tm1cli-0.1.7.dist-info/METADATA
tm1cli-0.1.7.dist-info/WHEEL
tm1cli-0.1.7.dist-info/entry_points.txt
tm1cli-0.1.7.dist-info/RECORD
