Metadata-Version: 2.3
Name: tm1cli
Version: 0.1.7
Summary: A command-line interface (CLI) tool for interacting with TM1 servers using TM1py.
License: MIT
Author: onefloid
Author-email: onefloid@gmx.de
Requires-Python: >=3.10,<4.0
Classifier: License :: OSI Approved :: MIT License
Classifier: Programming Language :: Python :: 3
Classifier: Programming Language :: Python :: 3.10
Classifier: Programming Language :: Python :: 3.11
Classifier: Programming Language :: Python :: 3.12
Classifier: Programming Language :: Python :: 3.13
Requires-Dist: TM1py (>=2.0.4,<3.0.0)
Requires-Dist: pyyaml (>=6.0.2,<7.0.0)
Requires-Dist: typer (>=0.13.1,<0.14.0)
Project-URL: Repository, https://github.com/onefloid/tm1cli
